fastshuffle.cpython-312-x86_64-linux-gnu.so
fastshuffle-1.0.1.dist-info/WHEEL
fastshuffle-1.0.1.dist-info/top_level.txt
fastshuffle-1.0.1.dist-info/LICENSE
fastshuffle-1.0.1.dist-info/RECORD
fastshuffle-1.0.1.dist-info/METADATA
