Metadata-Version: 2.1
Name: fastshuffle
Version: 1.0.1
Summary: Quickly shuffle parallel corpora
Home-page: https://github.com/LibreTranslate/FastShuffle
Author: Piero Toffanin
Author-email: pt@masseranolabs.com
Requires-Python: >=3.7
License-File: LICENSE
